cz_conventional_jira_commits.py
cz_conventional_jira_commits-0.4.0.dist-info/METADATA
cz_conventional_jira_commits-0.4.0.dist-info/WHEEL
cz_conventional_jira_commits-0.4.0.dist-info/top_level.txt
cz_conventional_jira_commits-0.4.0.dist-info/RECORD
