Metadata-Version: 2.1
Name: cz-conventional-jira-commits
Version: 0.4.0
Summary: UNKNOWN
Home-page: UNKNOWN
License: MIT
Platform: UNKNOWN
Requires-Dist: commitizen
Requires-Dist: gitpython
